waymo_open_dataset_tf_2_4_0-1.4.1.dist-info/LICENSE
waymo_open_dataset_tf_2_4_0-1.4.1.dist-info/top_level.txt
waymo_open_dataset_tf_2_4_0-1.4.1.dist-info/METADATA
waymo_open_dataset_tf_2_4_0-1.4.1.dist-info/RECORD
waymo_open_dataset_tf_2_4_0-1.4.1.dist-info/WHEEL
waymo_open_dataset/label_pb2.py
waymo_open_dataset/__init__.py
waymo_open_dataset/dataset_pb2.py
waymo_open_dataset/liblabel_cc_proto.so
waymo_open_dataset/libdataset_cc_proto.so
waymo_open_dataset/utils/test_utils.py
waymo_open_dataset/utils/box_utils.py
waymo_open_dataset/utils/__init__.py
waymo_open_dataset/utils/range_image_utils.py
waymo_open_dataset/utils/frame_utils.py
waymo_open_dataset/utils/transform_utils.py
waymo_open_dataset/math/libbox2d.so
waymo_open_dataset/math/libpolygon2d.so
waymo_open_dataset/math/libsegment2d.so
waymo_open_dataset/math/libexactfloat.so
waymo_open_dataset/common/libstatus.so
waymo_open_dataset/metrics/libmetrics_utils.so
waymo_open_dataset/metrics/libiou.so
waymo_open_dataset/metrics/libconfig_util.so
waymo_open_dataset/metrics/libmotion_metrics.so
waymo_open_dataset/metrics/libbreakdown_generator.so
waymo_open_dataset/metrics/libtest_utils.so
waymo_open_dataset/metrics/libdetection_metrics.so
waymo_open_dataset/metrics/__init__.py
waymo_open_dataset/metrics/libmotion_metrics_utils.so
waymo_open_dataset/metrics/libmatcher.so
waymo_open_dataset/metrics/libtracking_metrics.so
waymo_open_dataset/metrics/libmot.so
waymo_open_dataset/metrics/libhungarian.so
waymo_open_dataset/metrics/python/tracking_metrics.py
waymo_open_dataset/metrics/python/detection_metrics.py
waymo_open_dataset/metrics/python/__init__.py
waymo_open_dataset/metrics/python/motion_metrics.py
waymo_open_dataset/metrics/python/wod_detection_evaluator.py
waymo_open_dataset/metrics/python/config_util_py.py
waymo_open_dataset/metrics/ops/metrics_ops.so
waymo_open_dataset/metrics/ops/__init__.py
waymo_open_dataset/metrics/ops/libutils.so
waymo_open_dataset/metrics/ops/py_metrics_ops.py
waymo_open_dataset/protos/libbreakdown_cc_proto.so
waymo_open_dataset/protos/libmotion_metrics_cc_proto.so
waymo_open_dataset/protos/libscenario_cc_proto.so
waymo_open_dataset/protos/libmap_cc_proto.so
waymo_open_dataset/protos/__init__.py
